mosaic/__init__.py
mosaic/__main__.py
mosaic/_correlation_utils.py
mosaic/_typing.py
mosaic/clustering.py
mosaic/gridsearch.py
mosaic/similarity.py
mosaic/utils.py
mosaic_clustering-0.4.1.dist-info/LICENSE
mosaic_clustering-0.4.1.dist-info/METADATA
mosaic_clustering-0.4.1.dist-info/WHEEL
mosaic_clustering-0.4.1.dist-info/entry_points.txt
mosaic_clustering-0.4.1.dist-info/top_level.txt
mosaic_clustering-0.4.1.dist-info/RECORD
